usb_devices/__init__.py
usb_devices/py.typed
usb_devices-0.4.0.dist-info/LICENSE
usb_devices-0.4.0.dist-info/WHEEL
usb_devices-0.4.0.dist-info/METADATA
usb_devices-0.4.0.dist-info/RECORD
