Metadata-Version: 2.1
Name: usb-devices
Version: 0.4.0
Summary: Tools for mapping, describing, and resetting USB devices
Home-page: https://github.com/bluetooth-devices/usb-devices
License: MIT
Author: J. Nick Koston
Author-email: nick@koston.org
Requires-Python: >=3.9,<4.0
Classifier: Development Status :: 2 - Pre-Alpha
Classifier: Intended Audience :: Developers
Classifier: License :: OSI Approved :: MIT License
Classifier: Natural Language :: English
Classifier: Operating System :: OS Independent
Classifier: Programming Language :: Python :: 3
Classifier: Programming Language :: Python :: 3.9
Classifier: Programming Language :: Python :: 3.10
Classifier: Programming Language :: Python :: 3.11
Classifier: Topic :: Software Development :: Libraries
Project-URL: Bug Tracker, https://github.com/bluetooth-devices/usb-devices/issues
Project-URL: Changelog, https://github.com/bluetooth-devices/usb-devices/blob/main/CHANGELOG.md
Project-URL: Documentation, https://usb-devices.readthedocs.io
Project-URL: Repository, https://github.com/bluetooth-devices/usb-devices
